{
  "G": 9,
  "umax": 2.0,
  "tau": 2.0,
  "gammas": [
    2.0,
    2.0,
    2.0
  ],
  "h": 0.002,
  "method": "picard",
  "seed_array": "/home/user/REZN/results/full_ree/G6_tau2_gamma2_up_picard_0_prices.npz",
  "label": "gscan_G9_h0.002",
  "iterations": 400,
  "converged": false,
  "residual_inf": 0.0004878211071929683,
  "revelation_deficit": 0.009335635782442897,
  "slope": 0.9614349202674778,
  "max_fr_error": 0.00661966699084604,
  "elapsed_seconds": 404.922874212265,
  "representative_realization": {
    "u": [
      1.0,
      -1.0,
      1.0
    ],
    "price": 0.8807970779778822,
    "fr_price": 0.8807970779778823,
    "posteriors": [
      0.8807970779778824,
      0.8807970779778824,
      0.8807970779778824
    ]
  }
}