{
  "G_ladder": [
    {
      "G": 10,
      "tau": 2.0,
      "gamma": 0.5,
      "phi_resid_max": 0.18006825533343596,
      "phi_resid_med": 0.00022727110128873892,
      "phi_resid_l2": 0.06092563364447929,
      "viol_u": 0,
      "viol_p": 0,
      "1-R^2": 0.10779233322581583,
      "slope": 0.34401465722947977,
      "elapsed_s": 5.595612525939941,
      "good": true
    },
    {
      "G": 12,
      "tau": 2.0,
      "gamma": 0.5,
      "phi_resid_max": 0.4399927292948338,
      "phi_resid_med": 0.0003595189677055577,
      "phi_resid_l2": 0.15462064401625367,
      "viol_u": 0,
      "viol_p": 0,
      "1-R^2": 0.09834750531218017,
      "slope": 0.32757597542206884,
      "elapsed_s": 8.421043634414673,
      "good": true
    },
    {
      "G": 14,
      "tau": 2.0,
      "gamma": 0.5,
      "phi_resid_max": 0.43071952228879173,
      "phi_resid_med": 0.00043424831147230274,
      "phi_resid_l2": 0.1597460214760453,
      "viol_u": 0,
      "viol_p": 0,
      "1-R^2": 0.109635593976671,
      "slope": 0.31035288884283213,
      "elapsed_s": 11.88221001625061,
      "good": true
    },
    {
      "G": 16,
      "tau": 2.0,
      "gamma": 0.5,
      "phi_resid_max": 0.44722970558330427,
      "phi_resid_med": 0.0015370798400149467,
      "phi_resid_l2": 0.17039278284295464,
      "viol_u": 0,
      "viol_p": 0,
      "1-R^2": 0.10907959972825798,
      "slope": 0.31287127345246774,
      "elapsed_s": 15.534339904785156,
      "good": false
    },
    {
      "G": 18,
      "tau": 2.0,
      "gamma": 0.5,
      "phi_resid_max": 0.48714077398077005,
      "phi_resid_med": 0.0016191996112067918,
      "phi_resid_l2": 0.18008209384537693,
      "viol_u": 0,
      "viol_p": 0,
      "1-R^2": 0.11470658117486843,
      "slope": 0.3168095597802747,
      "elapsed_s": 20.942734003067017,
      "good": false
    },
    {
      "G": 20,
      "tau": 2.0,
      "gamma": 0.5,
      "phi_resid_max": 0.5275483422425249,
      "phi_resid_med": 0.0030382613325427577,
      "phi_resid_l2": 0.18691785742148473,
      "viol_u": 0,
      "viol_p": 0,
      "1-R^2": 0.11006812287097001,
      "slope": 0.3142878561874485,
      "elapsed_s": 26.623823404312134,
      "good": false
    },
    {
      "G": 24,
      "tau": 2.0,
      "gamma": 0.5,
      "phi_resid_max": 0.47190176015884655,
      "phi_resid_med": 0.00249360125762323,
      "phi_resid_l2": 0.1884816643353748,
      "viol_u": 0,
      "viol_p": 0,
      "1-R^2": 0.12302557262883884,
      "slope": 0.30616250055963307,
      "elapsed_s": 40.54146981239319,
      "good": false
    },
    {
      "G": 30,
      "tau": 2.0,
      "gamma": 0.5,
      "phi_resid_max": 0.4913863397394963,
      "phi_resid_med": 0.0028254831726706175,
      "phi_resid_l2": 0.18721011902731538,
      "viol_u": 0,
      "viol_p": 0,
      "1-R^2": 0.11859020230714079,
      "slope": 0.30395209387369976,
      "elapsed_s": 69.47255682945251,
      "good": false
    }
  ],
  "gamma_ladder": [
    {
      "G": 14,
      "tau": 2.0,
      "gamma": 2.0,
      "phi_resid_max": 0.915414134032924,
      "phi_resid_med": 0.008582483661699225,
      "phi_resid_l2": 0.16958909913128273,
      "viol_u": 0,
      "viol_p": 0,
      "1-R^2": 0.1065540375883105,
      "slope": 0.5859023547179812,
      "elapsed_s": 11.527526378631592,
      "good": false
    },
    {
      "G": 14,
      "tau": 2.0,
      "gamma": 1.0,
      "phi_resid_max": 0.46983788281935,
      "phi_resid_med": 0.001873116930955123,
      "phi_resid_l2": 0.1511645967405177,
      "viol_u": 0,
      "viol_p": 0,
      "1-R^2": 0.09944558957712168,
      "slope": 0.4509022443751074,
      "elapsed_s": 11.536384582519531,
      "good": false
    },
    {
      "G": 14,
      "tau": 2.0,
      "gamma": 0.5,
      "phi_resid_max": 0.43195572457046705,
      "phi_resid_med": 0.00045333746324544184,
      "phi_resid_l2": 0.15875444689502677,
      "viol_u": 0,
      "viol_p": 0,
      "1-R^2": 0.10997312927351333,
      "slope": 0.3102963975744723,
      "elapsed_s": 11.577438592910767,
      "good": true
    },
    {
      "G": 14,
      "tau": 2.0,
      "gamma": 0.3,
      "phi_resid_max": 0.4339924545173161,
      "phi_resid_med": 7.301327127312313e-05,
      "phi_resid_l2": 0.1514563733439149,
      "viol_u": 0,
      "viol_p": 0,
      "1-R^2": 0.09872684762764206,
      "slope": 0.28034666319951884,
      "elapsed_s": 11.448667526245117,
      "good": true
    },
    {
      "G": 14,
      "tau": 2.0,
      "gamma": 0.1,
      "phi_resid_max": 0.5876689571546585,
      "phi_resid_med": 2.7794668578810843e-06,
      "phi_resid_l2": 0.10563025035030978,
      "viol_u": 0,
      "viol_p": 0,
      "1-R^2": 0.09324417042506028,
      "slope": 0.2342250599642478,
      "elapsed_s": 11.366442203521729,
      "good": true
    }
  ],
  "tau_ladder": [
    {
      "G": 14,
      "tau": 2.0,
      "gamma": 0.5,
      "phi_resid_max": 0.43195572457046705,
      "phi_resid_med": 0.00045333746324544184,
      "phi_resid_l2": 0.15875444689502677,
      "viol_u": 0,
      "viol_p": 0,
      "1-R^2": 0.10997312927351333,
      "slope": 0.3102963975744723,
      "elapsed_s": 11.682820558547974,
      "good": true
    },
    {
      "G": 14,
      "tau": 1.0,
      "gamma": 0.5,
      "phi_resid_max": 0.42397552228305446,
      "phi_resid_med": 0.056495223648358,
      "phi_resid_l2": 0.17435425588008913,
      "viol_u": 0,
      "viol_p": 0,
      "1-R^2": 0.1778135721305122,
      "slope": 0.3810427389985251,
      "elapsed_s": 11.778031826019287,
      "good": false
    }
  ]
}