[
  {
    "G": 14,
    "status": "preexisting_strict",
    "max": NaN,
    "1-R^2": 0.1083
  },
  {
    "G": 15,
    "tau": 2.0,
    "gamma": 0.5,
    "max": 5.10702591327572e-15,
    "med": 2.220446049250313e-16,
    "u_viol": 0,
    "p_viol": 0,
    "1-R^2": 0.11257613796071109,
    "slope": 0.34073194146122066,
    "status": "strict_std_NK",
    "elapsed_s": 351.53733921051025
  },
  {
    "G": 16,
    "tau": 2.0,
    "gamma": 0.5,
    "max": 0.0756766744501075,
    "med": 7.591149930874508e-14,
    "u_viol": 0,
    "p_viol": 0,
    "1-R^2": 0.10497219912132782,
    "slope": 0.33908404733844233,
    "status": "non_strict_picard",
    "elapsed_s": 655.9279983043671
  }
]